readme_template_cli/src/__init__.py
readme_template_cli/src/generator.py
readme_template_cli/tests/__init__.py
readme_template_cli-0.1.3.dist-info/LICENSE
readme_template_cli-0.1.3.dist-info/METADATA
readme_template_cli-0.1.3.dist-info/WHEEL
readme_template_cli-0.1.3.dist-info/entry_points.txt
readme_template_cli-0.1.3.dist-info/RECORD
