Metadata-Version: 2.1
Name: readme-template-cli
Version: 0.1.3
Summary: Generate a README and other files for GitHub.
Home-page: https://github.com/Cutwell/readme-template
License: MIT
Author: Cutwell
Requires-Python: >=3.9,<4.0
Classifier: License :: OSI Approved :: MIT License
Classifier: Programming Language :: Python :: 3
Classifier: Programming Language :: Python :: 3.9
Classifier: Programming Language :: Python :: 3.10
Classifier: Programming Language :: Python :: 3.11
Requires-Dist: requests (>=2.31.0,<3.0.0)
Requires-Dist: tqdm (>=4.66.1,<5.0.0)
Project-URL: Repository, https://github.com/Cutwell/readme-template
